milvus_client/MilvusClient.py
milvus_client/__init__.py
milvus_client/async_post.py
milvus_client-1.0.1.dist-info/METADATA
milvus_client-1.0.1.dist-info/WHEEL
milvus_client-1.0.1.dist-info/licenses/LICENSE
milvus_client-1.0.1.dist-info/RECORD
